enconnect/__init__.py
enconnect/conftest.py
enconnect/fixtures.py
enconnect/py.typed
enconnect/version.txt
enconnect/discord/__init__.py
enconnect/discord/client.py
enconnect/discord/models.py
enconnect/discord/params.py
enconnect/discord/test/__init__.py
enconnect/discord/test/helpers.py
enconnect/discord/test/test_client.py
enconnect/discord/test/test_models.py
enconnect/hubitat/__init__.py
enconnect/hubitat/bridge.py
enconnect/hubitat/params.py
enconnect/hubitat/test/__init__.py
enconnect/hubitat/test/test_bridge.py
enconnect/instagram/__init__.py
enconnect/instagram/instagram.py
enconnect/instagram/models.py
enconnect/instagram/params.py
enconnect/instagram/test/__init__.py
enconnect/instagram/test/test_instagram.py
enconnect/instagram/test/test_models.py
enconnect/irc/__init__.py
enconnect/irc/client.py
enconnect/irc/models.py
enconnect/irc/params.py
enconnect/irc/test/__init__.py
enconnect/irc/test/helpers.py
enconnect/irc/test/test_client.py
enconnect/irc/test/test_models.py
enconnect/mattermost/__init__.py
enconnect/mattermost/client.py
enconnect/mattermost/models.py
enconnect/mattermost/params.py
enconnect/mattermost/test/__init__.py
enconnect/mattermost/test/helpers.py
enconnect/mattermost/test/test_client.py
enconnect/mattermost/test/test_models.py
enconnect/philips/__init__.py
enconnect/philips/bridge.py
enconnect/philips/params.py
enconnect/philips/test/__init__.py
enconnect/philips/test/helpers.py
enconnect/philips/test/test_bridge.py
enconnect/reddit/__init__.py
enconnect/reddit/models.py
enconnect/reddit/params.py
enconnect/reddit/reddit.py
enconnect/reddit/test/__init__.py
enconnect/reddit/test/test_models.py
enconnect/reddit/test/test_reddit.py
enconnect/ubiquiti/__init__.py
enconnect/ubiquiti/params.py
enconnect/ubiquiti/router.py
enconnect/ubiquiti/test/__init__.py
enconnect/ubiquiti/test/test_router.py
enconnect/utils/__init__.py
enconnect/utils/dummy.py
enconnect/utils/http.py
enconnect/utils/test/__init__.py
enconnect/utils/test/test_http.py
enconnect-0.17.19.dist-info/licenses/LICENSE
enconnect-0.17.19.dist-info/METADATA
enconnect-0.17.19.dist-info/WHEEL
enconnect-0.17.19.dist-info/top_level.txt
enconnect-0.17.19.dist-info/RECORD
