Metadata-Version: 2.4
Name: enconnect
Version: 0.17.19
Summary: Enasis Network Remote Connect
License: MIT
Project-URL: Source, https://github.com/enasisnetwork/enconnect
Project-URL: Documentation, https://enasisnetwork.github.io/enconnect/sphinx
Classifier: Programming Language :: Python :: 3
Classifier: Programming Language :: Python :: 3.11
Classifier: Programming Language :: Python :: 3.12
Requires-Python: >=3.11
License-File: LICENSE
Requires-Dist: encommon>=0.22.11
Requires-Dist: httpx>=0.28
Requires-Dist: websockets>=13.0
Dynamic: license-file
